crcengine/__init__.py
crcengine/__main__.py
crcengine/algorithms.py
crcengine/calc.py
crcengine/calc.py.bak
crcengine/codegen.py
crcengine/templates/c_template
crcengine/templates/h_template
crcengine/templates/test_template
crcengine-0.4.0.dist-info/entry_points.txt
crcengine-0.4.0.dist-info/LICENSE
crcengine-0.4.0.dist-info/METADATA
crcengine-0.4.0.dist-info/WHEEL
crcengine-0.4.0.dist-info/RECORD
