Metadata-Version: 2.1
Name: crcengine
Version: 0.4.0
Summary: A library for CRC calculation and code generation
Home-page: https://github.com/GardenTools/crcengine
License: GPL-3.0-only
Keywords: crcengine,CRC,cyclic,redundancy,check,checksum,code-generation,Castagnoli,CRC32,CRC16-CCITT
Author: Garden Tools
Author-email: gardensofdorwinion@gmail.com
Requires-Python: >=3.7.2,<4.0.0
Classifier: Development Status :: 4 - Beta
Classifier: Intended Audience :: Developers
Classifier: License :: OSI Approved :: GNU General Public License v3 (GPLv3)
Classifier: Natural Language :: English
Classifier: Programming Language :: C
Classifier: Programming Language :: Python :: 3
Classifier: Programming Language :: Python :: 3.8
Classifier: Programming Language :: Python :: 3.9
Classifier: Programming Language :: Python :: 3.10
Classifier: Programming Language :: Python :: 3.11
Classifier: Topic :: Communications
Classifier: Topic :: System :: Networking
Classifier: Topic :: Utilities
Requires-Dist: importlib-metadata (>=3.6) ; python_version < "3.8"
Requires-Dist: jinja2 (>=2.7)
Project-URL: Documentation, https://crcengine.readthedocs.io/en/latest/
Project-URL: Repository, https://github.com/GardenTools/crcengine
